{
  "kind": "collectionType",
  "collectionName": "projects",
  "info": {
    "singularName": "project",
    "pluralName": "projects",
    "displayName": "Project"
  },
  "options": {
    "draftAndPublish": true
  },
  "attributes": {
    "Title": {
      "type": "string"
    },
    "Description": {
      "type": "text"
    },
    "Image": {
      "allowedTypes": [
        "images",
        "files",
        "videos",
        "audios"
      ],
      "type": "media",
      "multiple": false
    }
  }
}
